setup.py
pyblish_starter/__init__.py
pyblish_starter/__main__.py
pyblish_starter/api.py
pyblish_starter/lib.py
pyblish_starter/pipeline.py
pyblish_starter/schema.py
pyblish_starter/version.py
pyblish_starter.egg-info/PKG-INFO
pyblish_starter.egg-info/SOURCES.txt
pyblish_starter.egg-info/dependency_links.txt
pyblish_starter.egg-info/requires.txt
pyblish_starter.egg-info/top_level.txt
pyblish_starter/maya/__init__.py
pyblish_starter/maya/lib.py
pyblish_starter/maya/pipeline.py
pyblish_starter/maya/pythonpath/userSetup.py
pyblish_starter/plugins/__init__.py
pyblish_starter/plugins/collect_instances.py
pyblish_starter/plugins/extract_animation.py
pyblish_starter/plugins/extract_model.py
pyblish_starter/plugins/extract_rig.py
pyblish_starter/plugins/extract_source.py
pyblish_starter/plugins/integrate_asset.py
pyblish_starter/plugins/validate_encapsulation.py
pyblish_starter/plugins/validate_model_hierarchy.py
pyblish_starter/plugins/validate_normals.py
pyblish_starter/plugins/validate_rig_hierarchy.py
pyblish_starter/plugins/validate_rig_members.py
pyblish_starter/plugins/validate_single_assembly.py
pyblish_starter/schema/asset.json
pyblish_starter/schema/container.json
pyblish_starter/schema/representation.json
pyblish_starter/schema/version.json
pyblish_starter/tools/__init__.py
pyblish_starter/tools/lib.py
pyblish_starter/tools/builder/__init__.py
pyblish_starter/tools/creator/__init__.py
pyblish_starter/tools/creator/app.py
pyblish_starter/tools/loader/__init__.py
pyblish_starter/tools/loader/app.py
pyblish_starter/tools/manager/__init__.py
pyblish_starter/vendor/Qt.py
pyblish_starter/vendor/__init__.py
pyblish_starter/vendor/jsonschema/__init__.py
pyblish_starter/vendor/jsonschema/__main__.py
pyblish_starter/vendor/jsonschema/_format.py
pyblish_starter/vendor/jsonschema/_reflect.py
pyblish_starter/vendor/jsonschema/_utils.py
pyblish_starter/vendor/jsonschema/_validators.py
pyblish_starter/vendor/jsonschema/cli.py
pyblish_starter/vendor/jsonschema/compat.py
pyblish_starter/vendor/jsonschema/exceptions.py
pyblish_starter/vendor/jsonschema/validators.py
pyblish_starter/vendor/jsonschema/schemas/draft3.json
